yta_editor_nodes_cpu/__init__.py
yta_editor_nodes_cpu/blender/__init__.py
yta_editor_nodes_cpu/blender/abstract.py
yta_editor_nodes_cpu/blender/add.py
yta_editor_nodes_cpu/blender/alpha.py
yta_editor_nodes_cpu/blender/mix.py
yta_editor_nodes_cpu/blender/utils.py
yta_editor_nodes_cpu/complex/__init__.py
yta_editor_nodes_cpu/complex/abstract.py
yta_editor_nodes_cpu/complex/display_over_at.py
yta_editor_nodes_cpu/compositor/__init__.py
yta_editor_nodes_cpu/compositor/abstract.py
yta_editor_nodes_cpu/compositor/displacement_with_rotation.py
yta_editor_nodes_cpu/processor/__init__.py
yta_editor_nodes_cpu/processor/abstract.py
yta_editor_nodes_cpu/processor/audio/__init__.py
yta_editor_nodes_cpu/processor/audio/abstract.py
yta_editor_nodes_cpu/processor/audio/experimental/__init__.py
yta_editor_nodes_cpu/processor/audio/experimental/chorus.py
yta_editor_nodes_cpu/processor/audio/volume.py
yta_editor_nodes_cpu/processor/black_and_white.py
yta_editor_nodes_cpu/processor/brightness.py
yta_editor_nodes_cpu/processor/color_contrast.py
yta_editor_nodes_cpu/processor/selection_mask.py
yta_editor_nodes_cpu/processor/video/__init__.py
yta_editor_nodes_cpu/processor/video/abstract.py
yta_editor_nodes_cpu/processor/video/transitions/__init__.py
yta_editor_nodes_cpu/processor/video/transitions/abstract.py
yta_editor_nodes_cpu/processor/video/transitions/slide.py
yta_editor_nodes_cpu/processor/video/waving_frame.py
yta_editor_nodes_cpu/utils.py
yta_editor_nodes_cpu-0.1.7.dist-info/licenses/LICENSE
yta_editor_nodes_cpu-0.1.7.dist-info/METADATA
yta_editor_nodes_cpu-0.1.7.dist-info/WHEEL
yta_editor_nodes_cpu-0.1.7.dist-info/RECORD
